webots_grpc/__init__.py
webots_grpc/__main__.py
webots_grpc/device_service.py
webots_grpc/distance_sensor_service.py
webots_grpc/motor_service.py
webots_grpc/position_sensor_service.py
webots_grpc/robot_service.py
webots_grpc/server.py
webots_grpc/generated/__init__.py
webots_grpc/generated/__init__.pyi
webots_grpc/generated/device_pb2.py
webots_grpc/generated/device_pb2.pyi
webots_grpc/generated/device_pb2_grpc.py
webots_grpc/generated/distance_sensor_pb2.py
webots_grpc/generated/distance_sensor_pb2.pyi
webots_grpc/generated/distance_sensor_pb2_grpc.py
webots_grpc/generated/motor_pb2.py
webots_grpc/generated/motor_pb2.pyi
webots_grpc/generated/motor_pb2_grpc.py
webots_grpc/generated/position_sensor_pb2.py
webots_grpc/generated/position_sensor_pb2.pyi
webots_grpc/generated/position_sensor_pb2_grpc.py
webots_grpc/generated/robot_pb2.py
webots_grpc/generated/robot_pb2.pyi
webots_grpc/generated/robot_pb2_grpc.py
webots_grpc/generated/sensor_pb2.py
webots_grpc/generated/sensor_pb2.pyi
webots_grpc/generated/sensor_pb2_grpc.py
webots_grpc-0.1.3.dist-info/METADATA
webots_grpc-0.1.3.dist-info/WHEEL
webots_grpc-0.1.3.dist-info/entry_points.txt
webots_grpc-0.1.3.dist-info/licenses/LICENSE
webots_grpc-0.1.3.dist-info/RECORD
