Metadata-Version: 2.4
Name: webots-grpc
Version: 0.1.3
Summary: A gRPC gateway for Webots robot simulation controllers, enabling remote control and integration.
Project-URL: Homepage, https://github.com/existedinnettw/webots-grpc
Project-URL: Repository, https://github.com/existedinnettw/webots-grpc
Author-email: insleker <bkinnightskytw@gmail.com>
License: MPL-2.0
License-File: LICENSE
Keywords: gateway,grpc,webots
Requires-Python: <3.14,>=3.10
Requires-Dist: grpcio-reflection<2,>=1.0.0
Requires-Dist: grpcio<2,>=1.71.0
Requires-Dist: python-dotenv>=1.1.1
